kalpa/__init__.py
kalpa/util.py
kalpa/tests/__init__.py
kalpa/tests/test_kalpa.py
kalpa-0.4.dist-info/DESCRIPTION.rst
kalpa-0.4.dist-info/METADATA
kalpa-0.4.dist-info/RECORD
kalpa-0.4.dist-info/WHEEL
kalpa-0.4.dist-info/metadata.json
kalpa-0.4.dist-info/top_level.txt
