Metadata-Version: 2.0
Name: kalpa
Version: 0.4
Summary: Resource baseclasses for traversal in Pyramid 
Home-page: https://github.com/edelooff/kalpa
Author: Elmer de Looff
Author-email: elmer.delooff@gmail.com
License: BSD
Keywords: pyramid traversal resource helper
Platform: UNKNOWN
Classifier: Development Status :: 3 - Alpha
Classifier: Framework :: Pyramid
Classifier: Intended Audience :: Developers
Classifier: License :: OSI Approved :: BSD License
Classifier: Programming Language :: Python
Classifier: Topic :: Internet :: WWW/HTTP
Requires-Dist: six
Provides-Extra: test
Requires-Dist: pyramid; extra == 'test'
Requires-Dist: pytest-runner; extra == 'test'
Requires-Dist: pytest; extra == 'test'
